bmnspeechlib/__init__.py
bmnspeechlib/convert_to_mono.py
bmnspeechlib/convert_to_wav.py
bmnspeechlib/core_analysis.py
bmnspeechlib/hf_access.py
bmnspeechlib/re_encode.py
bmnspeechlib/run.py
bmnspeechlib/speaker_recognition.py
bmnspeechlib/speechlib.py
bmnspeechlib/transcribe.py
bmnspeechlib/wav_segmenter.py
bmnspeechlib/whisper_sinhala.py
bmnspeechlib/write_log_file.py
bmnspeechlib-0.1.1.dist-info/METADATA
bmnspeechlib-0.1.1.dist-info/WHEEL
bmnspeechlib-0.1.1.dist-info/licenses/LICENSE
bmnspeechlib-0.1.1.dist-info/RECORD
