Metadata-Version: 2.3
Name: bmnspeechlib
Version: 0.1.1
Summary: A fork of speechlib with customizations for our team
Project-URL: Original Project, https://github.com/NavodPeiris/speechlib
Author-email: brandonatjoinpangia <brandon@joinpangia.com>
License: MIT License
Classifier: License :: OSI Approved :: MIT License
Classifier: Operating System :: OS Independent
Classifier: Programming Language :: Python :: 3
Requires-Python: >=3.8
Requires-Dist: accelerate==0.26.1
Requires-Dist: faster-whisper==1.0.3
Requires-Dist: pyannote-audio==3.1.1
Requires-Dist: pydub==0.25.1
Requires-Dist: speechbrain==0.5.16
Requires-Dist: torch==2.1.2
Requires-Dist: torchaudio==2.1.2
Requires-Dist: transformers==4.36.2
